pdf_combiner/__init__.py
pdf_combiner/cli.py
nish-0.1.0.dist-info/METADATA
nish-0.1.0.dist-info/WHEEL
nish-0.1.0.dist-info/entry_points.txt
nish-0.1.0.dist-info/top_level.txt
nish-0.1.0.dist-info/RECORD
